spf_engine/__init__.py
spf_engine/config.py
spf_engine/milter_spf.py
spf_engine/policyd_spf.py
spf_engine/policydspfsupp.py
spf_engine/policydspfuser.py
spf_engine/util.py
spf_engine-3.1.0.data/data/etc/init.d/pyspf-milter
spf_engine-3.1.0.data/data/etc/pyspf-milter/pyspf-milter.conf
spf_engine-3.1.0.data/data/etc/python-policyd-spf/policyd-spf.conf
spf_engine-3.1.0.data/data/etc/python-policyd-spf/policyd-spf.conf.commented
spf_engine-3.1.0.data/data/lib/systemd/system/pyspf-milter.service
spf_engine-3.1.0.data/data/share/doc/python-policyd-spf/README.per_user_whitelisting
spf_engine-3.1.0.data/data/share/man/man1/policyd-spf.1
spf_engine-3.1.0.data/data/share/man/man5/policyd-spf.conf.5
spf_engine-3.1.0.data/data/share/man/man5/policyd-spf.peruser.5
spf_engine-3.1.0.data/data/share/man/man8/pyspf-milter.8
spf_engine-3.1.0.dist-info/entry_points.txt
spf_engine-3.1.0.dist-info/COPYING
spf_engine-3.1.0.dist-info/WHEEL
spf_engine-3.1.0.dist-info/METADATA
spf_engine-3.1.0.dist-info/RECORD
