Metadata-Version: 2.1
Name: spf-engine
Version: 3.1.0
Summary: SPF (Sender Policy Framework) processing engine for Postfix policy server and Milter implemented in Python.
Keywords: Postfix,Sendmail,milter,spf,email
Author-email: Scott Kitterman <scott@kitterman.com>
Requires-Python: >=3.3
Classifier: Development Status :: 5 - Production/Stable
Classifier: Environment :: No Input/Output (Daemon)
Classifier: Intended Audience :: Developers
Classifier: License :: OSI Approved :: Apache Software License
Classifier: Natural Language :: English
Classifier: Operating System :: POSIX
Classifier: Programming Language :: Python :: 3
Classifier: Topic :: Communications :: Email :: Mail Transport Agents
Classifier: Topic :: Communications :: Email :: Filters
Requires-Dist: pyspf
Requires-Dist: authres
Requires-Dist: pymilter ; extra == "milter"
Project-URL: Home, https://launchpad.net/spf-engine
Provides-Extra: milter
